bs2json/__init__.py
bs2json/bs2json.py
bs2json-0.1.2.dist-info/LICENSE
bs2json-0.1.2.dist-info/METADATA
bs2json-0.1.2.dist-info/WHEEL
bs2json-0.1.2.dist-info/top_level.txt
bs2json-0.1.2.dist-info/RECORD
