Metadata-Version: 2.1
Name: bs2json
Version: 0.1.2
Summary: Convert bs4 Tags into Json
Home-page: https://github.com/MrDebugger/bs2json
Author: Ijaz Ur Rahim
Author-email: ijazkhan095@gmail.com
License: MIT
Keywords: parser,html,bs4,BeautifulSoup,soup,bs4,bs2json,json
Platform: UNKNOWN
Classifier: License :: OSI Approved :: MIT License
Classifier: Programming Language :: Python :: 3
Requires-Dist: bs4 (>=0.0.1)
